Workbook

Sheet Kalkulation
A1: PlayStation 5 Pro — Kaufkalkulation
A2: Alle Beträge in Euro · Blaue Zahlen = Eingaben, die du ändern kannst · Schwarze Zahlen = berechnet · Grüne Zahlen = von einem anderen Blatt
A4: 1. Eingaben
A5: Position | B5: Wert | C5: Hinweis
A6: Listenpreis PS5 Pro | B6: 899.99 | C6: Bestätigt: 899,99 € ist die offizielle UVP seit der Preiserhöhung vom 02.04.2026. Deine Zwischenwerte 482,99 / 432,99 gehen damit exakt auf.
A7: Warenkorb-Rabatt (sofort) | B7: 45 | C7: Wird direkt im Warenkorb abgezogen.
A8: Eintauschwert PS5 Slim | B8: 372 | C8: Betrag, den du für die alte Konsole bekommst.
A9: Eintausch-Bonus von PlayStation | B9: 50 | C9: Zusätzlicher Gutschein, nur bei Eintausch — nicht bei Privatverkauf.
A10: PSN-Karte — Nennwert | B10: 50 | C10: Guthaben, das die Karte auf dem Konto gutschreibt.
A11: PSN-Karte — dein Kaufpreis | B11: 45.49 | C11: Dein gefundener Preis. Es geht deutlich günstiger — siehe Blatt "PSN-Karten".
A13: 2. Rechenweg bis zum Eigenanteil
A14: Listenpreis PS5 Pro | B14: =B6 -> 899.99
A15: abzüglich Warenkorb-Rabatt | B15: =-B7 -> -45
A16: Preis im Warenkorb | B16: =SUM(B14:B15) -> 854.99 | C16: Das steht an der Kasse.
A17: abzüglich Eintauschwert PS5 Slim | B17: =-B8 -> -372
A18: Zwischensumme | B18: =SUM(B16:B17) -> 482.99 | C18: Deine genannten 482,99 €.
A19: abzüglich Eintausch-Bonus | B19: =-B9 -> -50
A20: Eigenanteil — so viel zahlst du selbst | B20: =SUM(B18:B19) -> 432.99 | C20: Deine genannten 432,99 €. Basis für alles Weitere.
A22: 3. Zahlung mit vergünstigten PSN-Guthabenkarten
A23: Details und Stückzahlen auf dem Blatt "PSN-Karten".
A25: Ersparnis pro Karte | B25: =B10-B11 -> 4.51 | C25: Nennwert minus Kaufpreis.
A26: Rabatt in Prozent | B26: =(B10-B11)/B10 -> 0.0902 | C26: Zum Vergleich: seriöse Anbieter liegen bei 12-18 %.
A27: Variante A — nur volle Karten, Rest bar | B27: ='PSN-Karten'!B18 -> 396.91 | C27: Empfohlen: kein Restguthaben, das liegen bleibt.
A28: Variante B — aufrunden, Barkosten | B28: ='PSN-Karten'!B25 -> 409.41 | C28: Höhere Barkosten, dafür bleibt Guthaben übrig.
A29: Variante B — Restguthaben danach | B29: ='PSN-Karten'!B24 -> 17.01 | C29: Nur etwas wert, wenn du es wirklich für Spiele ausgibst.
A31: 4. Gegenprobe: Eintausch oder lieber privat verkaufen?
A32: Eintausch bringt insgesamt | B32: =B8+B9 -> 422 | C32: Eintauschwert plus Bonus.
A33: Privatverkauf lohnt sich ab | B33: =B8+B9+0.01 -> 422.01 | C33: Erst oberhalb dieses Preises ist ein privater Verkauf besser.
A34: Barwert des Bonus, falls PSN-Guthaben | B34: =B9/B10*B11 -> 45.49 | C34: Ein 50-€-PSN-Gutschein ist real nur so viel wert, wie er als Karte kostet.
A35: Eintausch bar bewertet | B35: =B8+B9/B10*B11 -> 417.49 | C35: Realistischere Vergleichsschwelle, wenn der Bonus PSN-Guthaben ist.
A37: 5. Wichtige Hinweise
A38: • KRITISCH ZUERST PRÜFEN: Kann die Konsole überhaupt mit PSN-Guthaben bezahlt werden? Bei PlayStation Direct gilt Wallet-Guthaben üblicherweise nur für Spiele, Add-ons und Abos, nicht für Hardware. Klappt es nicht, fällt die gesamte Kartenrechnung weg und du bleibst beim Eigenanteil aus Zeile 20.
A39: • Die 372 € und der 50-€-Bonus gehören zum selben Vorgang: Du kannst die Slim entweder eintauschen ODER privat verkaufen, nicht beides.
A40: • Ist der 50-€-Bonus ein PSN-Gutschein statt Bargeld, sinkt sein echter Wert auf den Kartenpreis (Zeile 34).
A41: • Deutlich mehr Sparmöglichkeiten stehen auf dem Blatt "Sparhebel" — dort liegt das meiste Geld.
A42: • Preise und Konditionen aus deinen Angaben vom 12.08.2026, ergänzt um recherchierte Marktdaten. Vor dem Kauf selbst gegenprüfen.

Sheet PSN-Karten
A1: PSN-Guthabenkarten — wie viele, und zu welchem Preis?
A2: Grüne Zahlen kommen vom Blatt "Kalkulation".
A4: Ausgangslage
A5: Eigenanteil laut Kalkulation | B5: =Kalkulation!B20 -> 432.99
A6: Nennwert je Karte | B6: =Kalkulation!B10 -> 50
A7: Kaufpreis je Karte | B7: =Kalkulation!B11 -> 45.49
A8: Ersparnis je Karte | B8: =B6-B7 -> 4.51
A9: Rabatt in Prozent | B9: =B8/B6 -> 0.0902
A11: Variante A — nur volle Karten kaufen, Rest normal bezahlen
A12: Rechnerisch benötigte Karten | B12: =B5/B6 -> 8.6598 | C12: Eigenanteil geteilt durch den Nennwert.
A13: Karten kaufen (abgerundet) | B13: =ROUNDDOWN(B5/B6,0) -> 8 | C13: Nur volle Karten.
A14: Damit gekauftes Guthaben | B14: =B13*B6 -> 400
A15: Kosten der Karten | B15: =B13*B7 -> 363.92
A16: Restbetrag normal bezahlen | B16: =B5-B14 -> 32.99 | C16: Per Karte oder PayPal, ohne Rabatt.
A17: Restguthaben übrig | B17: =0 -> 0 | C17: Es bleibt nichts liegen — der große Vorteil dieser Variante.
A18: Gesamtkosten Variante A | B18: =B15+B16 -> 396.91 | C18: Das zahlst du am Ende wirklich.
A19: Ersparnis gegenüber Direktzahlung | B19: =B5-B18 -> 36.08
A21: Variante B — aufrunden und alles mit Guthaben bezahlen
A22: Karten kaufen (aufgerundet) | B22: =ROUNDUP(B5/B6,0) -> 9
A23: Damit gekauftes Guthaben | B23: =B22*B6 -> 450
A24: Restguthaben nach dem Kauf | B24: =B23-B5 -> 17.01 | C24: Bleibt auf dem PSN-Konto liegen.
A25: Barkosten Variante B | B25: =B22*B7 -> 409.41 | C25: Höher als Variante A — du kaufst Guthaben auf Vorrat.
A26: Ersparnis gegenüber Direktzahlung | B26: =B5-B25 -> 23.58
A27: Effektive Kosten, Restguthaben voll gerechnet | B27: =B25-B24 -> 392.4 | C27: Nur gültig, wenn du die restlichen Euro sicher für Spiele ausgibst.
A29: Übersicht: Karten, Guthaben und Ersparnis
A30: Karten | B30: Guthaben | C30: Kosten | D30: Ersparnis | E30: Rest zum Eigenanteil
A31: 1 | B31: =A31*$B$6 -> 50 | C31: =A31*$B$7 -> 45.49 | D31: =A31*($B$6-$B$7) -> 4.51 | E31: =MAX(0,$B$5-B31) -> 382.99
A32: 2 | B32: =A32*$B$6 -> 100 | C32: =A32*$B$7 -> 90.98 | D32: =A32*($B$6-$B$7) -> 9.02 | E32: =MAX(0,$B$5-B32) -> 332.99
A33: 3 | B33: =A33*$B$6 -> 150 | C33: =A33*$B$7 -> 136.47 | D33: =A33*($B$6-$B$7) -> 13.53 | E33: =MAX(0,$B$5-B33) -> 282.99
A34: 4 | B34: =A34*$B$6 -> 200 | C34: =A34*$B$7 -> 181.96 | D34: =A34*($B$6-$B$7) -> 18.04 | E34: =MAX(0,$B$5-B34) -> 232.99
A35: 5 | B35: =A35*$B$6 -> 250 | C35: =A35*$B$7 -> 227.45 | D35: =A35*($B$6-$B$7) -> 22.55 | E35: =MAX(0,$B$5-B35) -> 182.99
A36: 6 | B36: =A36*$B$6 -> 300 | C36: =A36*$B$7 -> 272.94 | D36: =A36*($B$6-$B$7) -> 27.06 | E36: =MAX(0,$B$5-B36) -> 132.99
A37: 7 | B37: =A37*$B$6 -> 350 | C37: =A37*$B$7 -> 318.43 | D37: =A37*($B$6-$B$7) -> 31.57 | E37: =MAX(0,$B$5-B37) -> 82.99
A38: 8 | B38: =A38*$B$6 -> 400 | C38: =A38*$B$7 -> 363.92 | D38: =A38*($B$6-$B$7) -> 36.08 | E38: =MAX(0,$B$5-B38) -> 32.99
A39: 9 | B39: =A39*$B$6 -> 450 | C39: =A39*$B$7 -> 409.41 | D39: =A39*($B$6-$B$7) -> 40.59 | E39: =MAX(0,$B$5-B39) -> 0
A40: 10 | B40: =A40*$B$6 -> 500 | C40: =A40*$B$7 -> 454.9 | D40: =A40*($B$6-$B$7) -> 45.1 | E40: =MAX(0,$B$5-B40) -> 0
A41: 11 | B41: =A41*$B$6 -> 550 | C41: =A41*$B$7 -> 500.39 | D41: =A41*($B$6-$B$7) -> 49.61 | E41: =MAX(0,$B$5-B41) -> 0
A42: 12 | B42: =A42*$B$6 -> 600 | C42: =A42*$B$7 -> 545.88 | D42: =A42*($B$6-$B$7) -> 54.12 | E42: =MAX(0,$B$5-B42) -> 0
A45: Was bringt eine günstigere Bezugsquelle?
A46: Recherchierte Marktpreise für 50 € PSN-Guthaben (Stand August 2026). Alle Zeilen rechnen mit der Kartenzahl aus Variante A.
A47: Kaufpreis je 50 € | B47: Rabatt | C47: Kosten der Karten | D47: Restbetrag bar | E47: Gesamt | F47: Mehrersparnis
A48: 45.49 | B48: =($B$6-A48)/$B$6 -> 0.0902 | C48: =$B$13*A48 -> 363.92 | D48: =$B$16 -> 32.99 | E48: =C48+D48 -> 396.91 | F48: =$B$18-E48 -> 0 | G48: Dein aktueller Preis
A49: 43.99 | B49: =($B$6-A49)/$B$6 -> 0.1202 | C49: =$B$13*A49 -> 351.92 | D49: =$B$16 -> 32.99 | E49: =C49+D49 -> 384.91 | F49: =$B$18-E49 -> 12 | G49: Häufige Aktionspreise im Handel
A50: 41.99 | B50: =($B$6-A50)/$B$6 -> 0.1602 | C50: =$B$13*A50 -> 335.92 | D50: =$B$16 -> 32.99 | E50: =C50+D50 -> 368.91 | F50: =$B$18-E50 -> 28 | G50: Gut erreichbar bei Deal-Portalen
A51: 39.99 | B51: =($B$6-A51)/$B$6 -> 0.2002 | C51: =$B$13*A51 -> 319.92 | D51: =$B$16 -> 32.99 | E51: =C51+D51 -> 352.91 | F51: =$B$18-E51 -> 44 | G51: Nur bei starken Aktionen
A52: 37.5 | B52: =($B$6-A52)/$B$6 -> 0.25 | C52: =$B$13*A52 -> 300 | D52: =$B$16 -> 32.99 | E52: =C52+D52 -> 332.99 | F52: =$B$18-E52 -> 63.92 | G52: Beworbener Bestpreis — Anbieter genau prüfen
A54: Achtung bei Grauimport-Shops: sehr günstige Codes stammen teils aus fremden Regionen oder aus Rückbuchungen. Ein gesperrter Code oder Account kostet mehr, als die Ersparnis bringt. Halte dich an etablierte Händler mit deutscher Region und Käuferschutz.

Sheet Sparhebel
A1: Alle Sparhebel im Überblick
A2: So arbeitest du damit: Trage in der Spalte "Nutzen?" für jeden Hebel Ja, Nein oder Prüfen ein. Nur "Ja" zählt in die gesicherte Ersparnis; "Prüfen" fließt zusätzlich ins Maximalpotenzial.
A4: Stellschrauben — hier drehst du an den Annahmen
A5: Bester gefundener Marktpreis der Konsole | B5: 798.9 | F5: Preisvergleiche listen die Pro deutlich unter der UVP von 899,99 €. Trage den Preis ein, den du wirklich findest.
A6: Cashback-Portal — Quote | B6: 0.03 | F6: Shoop, iGraal & Co. liegen bei 1-5 %. Konsolen sind oft ausgeschlossen — Bedingungen lesen.
A7: Kreditkarten-/Payback-Cashback | B7: 0.01 | F7: Je nach Karte 0,5-2 % auf den Umsatz.
A8: Corporate Benefits / Mitarbeiterrabatt | B8: 0.03 | F8: Über Arbeitgeberportale oft 3-10 % bei großen Elektronikhändlern.
A9: Newsletter-Gutschein für Neukunden | B9: 10 | F9: Typisch 5-15 €, meist mit Mindestbestellwert.
A10: Punkteaktion auf Guthabenkarten | B10: 0.05 | F10: Supermärkte fahren regelmäßig 10-20fach-Punkte auf PSN-Karten. Basis ist der Kartenwert.
A11: Preis der günstigsten seriösen PSN-Karte | B11: 41.99 | F11: Recherchiert: 41-42 € sind bei Deal-Portalen gut erreichbar.
A12: Wert des Disc-Laufwerks der Slim | B12: 79.99 | F12: UVP des abnehmbaren Laufwerks CFI-ZDD1.
A13: Erwarteter Privatverkaufspreis der Slim | B13: 372 | F13: Was du bei Kleinanzeigen realistisch bekommst.
A15: Die Hebel
A16: Hebel | B16: Ersparnis | C16: Nutzen? | D16: Zählt sicher | E16: Max. möglich | F16: Worauf du achten musst
A17: A — Am Kaufpreis der Konsole selbst sparen
A18: Woanders kaufen statt zur UVP bei PlayStation Direct | B18: =MAX(0,Kalkulation!B16-$B$5-Kalkulation!B9) -> 6.09 | C18: Prüfen | D18: =IF(C18="Ja",B18,0) -> 0 | E18: =IF(OR(C18="Ja",C18="Prüfen"),B18,0) -> 6.09 | F18: Gegenrechnung: Der günstigere Händler spart am Preis, kostet dich aber den 50-€-Eintauschbonus. Nur der Nettovorteil steht hier.
A19: Auf Aktionswoche oder Black Friday warten | B19: 50 | C19: Nein | D19: =IF(C19="Ja",B19,0) -> 0 | E19: =IF(OR(C19="Ja",C19="Prüfen"),B19,0) -> 0 | F19: ALTERNATIVE zum Hebel darüber — nur einer davon kann gelten. Auf "Ja" setzen, wenn du diesen Weg wählst. Trage ein, was du dir vom Warten erwartest.
A20: Refurbished von Sony oder B-Ware statt Neuware | B20: 90 | C20: Nein | D20: =IF(C20="Ja",B20,0) -> 0 | E20: =IF(OR(C20="Ja",C20="Prüfen"),B20,0) -> 0 | F20: ALTERNATIVE zu den Hebeln darüber. Mit Herstellergarantie, eventuell leichte Gebrauchsspuren.
A21: Bundle kaufen und beiliegendes Spiel weiterverkaufen | B21: 30 | C21: Nein | D21: =IF(C21="Ja",B21,0) -> 0 | E21: =IF(OR(C21="Ja",C21="Prüfen"),B21,0) -> 0 | F21: ALTERNATIVE zu den Hebeln darüber. Lohnt nur, wenn das Bundle nicht teurer ist als die nackte Konsole.
A22: B — Rabatte, die oben drauf kommen
A23: Cashback-Portal vorschalten | B23: =Kalkulation!B16*$B$6 -> 25.6497 | C23: Prüfen | D23: =IF(C23="Ja",B23,0) -> 0 | E23: =IF(OR(C23="Ja",C23="Prüfen"),B23,0) -> 25.6497 | F23: Vor dem Kauf über das Portal einsteigen, sonst zählt es nicht. Konsolen sind häufig ausgeschlossen.
A24: Kreditkarten- oder Payback-Cashback | B24: =Kalkulation!B16*$B$7 -> 8.5499 | C24: Prüfen | D24: =IF(C24="Ja",B24,0) -> 0 | E24: =IF(OR(C24="Ja",C24="Prüfen"),B24,0) -> 8.5499 | F24: Läuft automatisch über die Zahlungsart, lässt sich meist mit allem kombinieren.
A25: Corporate Benefits / Mitarbeiterrabatt | B25: =Kalkulation!B16*$B$8 -> 25.6497 | C25: Nein | D25: =IF(C25="Ja",B25,0) -> 0 | E25: =IF(OR(C25="Ja",C25="Prüfen"),B25,0) -> 0 | F25: ALTERNATIVE zum Cashback-Portal — beide verlangen einen eigenen Kaufweg. Wenn dein Arbeitgeber ein Portal hat, hier auf "Ja" und Cashback auf "Nein".
A26: Newsletter-Gutschein als Neukunde | B26: =$B$9 -> 10 | C26: Prüfen | D26: =IF(C26="Ja",B26,0) -> 0 | E26: =IF(OR(C26="Ja",C26="Prüfen"),B26,0) -> 10 | F26: Einmalig pro Händler, oft mit Mindestbestellwert.
A27: Punkteaktion auf Guthabenkarten mitnehmen | B27: ='PSN-Karten'!B14*$B$10 -> 20 | C27: Prüfen | D27: =IF(C27="Ja",B27,0) -> 0 | E27: =IF(OR(C27="Ja",C27="Prüfen"),B27,0) -> 20 | F27: Karten im Supermarkt während einer Punkteaktion kaufen. Punkte anschließend in Prämien oder Cent umwandeln.
A28: Günstigere PSN-Kartenquelle nutzen | B28: ='PSN-Karten'!B13*('PSN-Karten'!B7-$B$11) -> 28 | C28: Prüfen | D28: =IF(C28="Ja",B28,0) -> 0 | E28: =IF(OR(C28="Ja",C28="Prüfen"),B28,0) -> 28 | F28: Dein Preis liegt bei 45,49 €, gut erreichbar sind 41-42 €. Nur seriöse Händler mit deutscher Region.
A29: C — Kosten vermeiden und Zusatzerlöse
A30: Disc-Laufwerk der Slim behalten statt mitzugeben | B30: =$B$12 -> 79.99 | C30: Prüfen | D30: =IF(C30="Ja",B30,0) -> 0 | E30: =IF(OR(C30="Ja",C30="Prüfen"),B30,0) -> 79.99 | F30: Bestätigt: Das abnehmbare Laufwerk CFI-ZDD1 der PS5 Slim passt an die PS5 Pro. Vor dem Eintausch klären, ob es abgegeben werden muss — sonst verschenkst du ein 79,99-€-Teil.
A31: Privatverkauf statt Eintausch, falls er mehr bringt | B31: =MAX(0,$B$13-Kalkulation!B8-Kalkulation!B9) -> 0 | C31: Prüfen | D31: =IF(C31="Ja",B31,0) -> 0 | E31: =IF(OR(C31="Ja",C31="Prüfen"),B31,0) -> 0 | F31: Zählt nur, was über Eintauschwert plus Bonus hinausgeht. Bei 372 € Erwartung ist der Eintausch besser.
A32: Vorhandenes Zubehör weiternutzen | B32: 0 | C32: Ja | D32: =IF(C32="Ja",B32,0) -> 0 | E32: =IF(OR(C32="Ja",C32="Prüfen"),B32,0) -> 0 | F32: DualSense, HDMI-Kabel und Standfuß der Slim passen weiter. Kostet nichts und spart Neukäufe.
A33: Nachträgliche Preisgarantie geltend machen | B33: 0 | C33: Prüfen | D33: =IF(C33="Ja",B33,0) -> 0 | E33: =IF(OR(C33="Ja",C33="Prüfen"),B33,0) -> 0 | F33: Manche Händler erstatten die Differenz, wenn der Preis binnen 14-30 Tagen fällt. Nach dem Kauf beobachten.
A34: Spiele und Zubehör der Slim separat verkaufen | B34: 0 | C34: Prüfen | D34: =IF(C34="Ja",B34,0) -> 0 | E34: =IF(OR(C34="Ja",C34="Prüfen"),B34,0) -> 0 | F34: Discs, Zweitcontroller und Ladestationen bringen einzeln oft mehr als im Paket.
A36: Was dabei herauskommt
A37: Bester Plan bisher (Variante A) | B37: ='PSN-Karten'!B18 -> 396.91 | F37: Aus dem Blatt "PSN-Karten" — Stand vor den Hebeln dieser Seite.
A38: Gesicherte Zusatzersparnis | B38: =SUM(D18:D34) -> 0 | F38: Summe aller Hebel, die du auf "Ja" gesetzt hast.
A39: Zusätzlich möglich, wenn die Prüfungen klappen | B39: =SUM(E18:E34)-SUM(D18:D34) -> 178.2796 | F39: Alles, was noch auf "Prüfen" steht.
A40: Endpreis mit gesicherten Hebeln | B40: =MAX(0,'PSN-Karten'!B18-SUM(D18:D34)) -> 396.91 | F40: Das zahlst du nach heutigem Stand.
A41: Endpreis, wenn alle Hebel greifen | B41: =MAX(0,'PSN-Karten'!B18-SUM(E18:E34)) -> 218.6304 | F41: Optimistisch — mehrere Hebel schließen sich in der Praxis gegenseitig aus.
A43: Warum das Best-Case-Ergebnis nicht wörtlich zu nehmen ist: "Woanders kaufen", "Refurbished" und "Auf Aktion warten" beschreiben denselben Kauf auf drei Wegen — du kannst nur einen gehen. Ebenso schließen sich Cashback-Portal und Corporate Benefits meist aus, weil beide einen eigenen Kaufweg verlangen. Setze diese Zeilen bewusst auf "Nein", sobald du dich entschieden hast, dann stimmt die Summe.

Sheet Szenarien
A1: Szenarien im Vergleich
A2: Von "nichts tun" bis "alles mitnehmen" — jede Zeile baut auf der vorherigen auf.
A4: Szenario | B4: Kosten für dich | C4: Ersparnis | D4: Was du dafür tun musst
A5: 1 — Einfach zum Listenpreis kaufen | B5: =Kalkulation!B6 -> 899.99 | C5: =$B$5-B5 -> 0 | D5: Nichts. Referenzwert für alle Vergleiche.
A6: 2 — Mit Warenkorb-Rabatt | B6: =Kalkulation!B16 -> 854.99 | C6: =$B$5-B6 -> 45 | D6: Rabatt wird automatisch abgezogen.
A7: 3 — Plus Eintausch der PS5 Slim | B7: =Kalkulation!B18 -> 482.99 | C7: =$B$5-B7 -> 417 | D7: Alte Konsole einschicken bzw. abgeben.
A8: 4 — Plus 50-€-Eintausch-Bonus | B8: =Kalkulation!B20 -> 432.99 | C8: =$B$5-B8 -> 467 | D8: Eintausch über die Bonus-Aktion abwickeln.
A9: 5 — Plus PSN-Karten zu 45,49 € | B9: ='PSN-Karten'!B18 -> 396.91 | C9: =$B$5-B9 -> 503.08 | D9: Volle Karten günstig kaufen, Rest normal zahlen.
A10: 6 — Plus PSN-Karten, aufgerundet | B10: ='PSN-Karten'!B25 -> 409.41 | C10: =$B$5-B10 -> 490.58 | D10: Höhere Barkosten, Restguthaben bleibt übrig.
A11: 7 — Plus gesicherte Sparhebel | B11: =Sparhebel!B40 -> 396.91 | C11: =$B$5-B11 -> 503.08 | D11: Alle Hebel, die auf "Ja" stehen.
A12: 8 — Best Case, alle Hebel greifen | B12: =Sparhebel!B41 -> 218.6304 | C12: =$B$5-B12 -> 681.3596 | D12: Optimistisch — siehe Warnung auf dem Blatt "Sparhebel".
A14: Ergebnis
A15: Realistisch günstigste Variante | B15: =MIN(B5:B11) -> 396.91 | D15: Ohne das optimistische Best-Case-Szenario 8.
A16: Ersparnis gegenüber Listenpreis | B16: =B5-MIN(B5:B11) -> 503.08
A17: Ersparnis in Prozent | B17: =(B5-MIN(B5:B11))/B5 -> 0.55898399
A18: Best Case inklusive Szenario 8 | B18: =MIN(B5:B12) -> 218.6304 | D18: Nur erreichbar, wenn sich die Hebel nicht gegenseitig ausschließen.
A20: Reihenfolge fürs Vorgehen: 1. Klären, ob die Konsole überhaupt mit PSN-Guthaben bezahlbar ist. 2. Preis der Konsole beim günstigsten seriösen Händler gegen das PS-Direct-Paket aus Rabatt und Eintauschbonus rechnen. 3. Vor dem Eintausch das Disc-Laufwerk sichern. 4. Guthabenkarten erst kurz vor dem Kauf und nur bei einer laufenden Aktion holen.
